[
{"year":"1899","deaths":"26","vehicle_miles_traveled_billions":"","populatiom":"76212168","alcohol_related_best":"","alcohol_related_derived":""},
{"year":"1900","deaths":"36","vehicle_miles_traveled_billions":"","populatiom":"76094000","alcohol_related_best":"","alcohol_related_derived":""},
{"year":"1901","deaths":"54","vehicle_miles_traveled_billions":"","populatiom":"77584000","alcohol_related_best":"","alcohol_related_derived":""},
{"year":"1902","deaths":"79","vehicle_miles_traveled_billions":"","populatiom":"79163000","alcohol_related_best":"","alcohol_related_derived":""},
{"year":"1903","deaths":"117","vehicle_miles_traveled_billions":"","populatiom":"80632000","alcohol_related_best":"","alcohol_related_derived":""},
{"year":"1904","deaths":"172","vehicle_miles_traveled_billions":"","populatiom":"82166000","alcohol_related_best":"","alcohol_related_derived":""},
{"year":"1905","deaths":"252","vehicle_miles_traveled_billions":"","populatiom":"83822000","alcohol_related_best":"","alcohol_related_derived":""},
{"year":"1906","deaths":"338","vehicle_miles_traveled_billions":"","populatiom":"85450000","alcohol_related_best":"","alcohol_related_derived":""},
{"year":"1907","deaths":"581","vehicle_miles_traveled_billions":"","populatiom":"87008000","alcohol_related_best":"","alcohol_related_derived":""},
{"year":"1908","deaths":"751","vehicle_miles_traveled_billions":"","populatiom":"88710000","alcohol_related_best":"","alcohol_related_derived":""},
{"year":"1909","deaths":"1174","vehicle_miles_traveled_billions":"","populatiom":"90490000","alcohol_related_best":"","alcohol_related_derived":""},
{"year":"1910","deaths":"1599","vehicle_miles_traveled_billions":"","populatiom":"92407000","alcohol_related_best":"","alcohol_related_derived":""},
{"year":"1911","deaths":"2043","vehicle_miles_traveled_billions":"","populatiom":"93863000","alcohol_related_best":"","alcohol_related_derived":""},
{"year":"1912","deaths":"2968","vehicle_miles_traveled_billions":"","populatiom":"95335000","alcohol_related_best":"","alcohol_related_derived":""},
{"year":"1913","deaths":"4079","vehicle_miles_traveled_billions":"","populatiom":"97225000","alcohol_related_best":"","alcohol_related_derived":""},
{"year":"1914","deaths":"4468","vehicle_miles_traveled_billions":"","populatiom":"99111000","alcohol_related_best":"","alcohol_related_derived":""},
{"year":"1915","deaths":"6779","vehicle_miles_traveled_billions":"","populatiom":"100546000","alcohol_related_best":"","alcohol_related_derived":""},
{"year":"1916","deaths":"7766","vehicle_miles_traveled_billions":"","populatiom":"101961000","alcohol_related_best":"","alcohol_related_derived":""},
{"year":"1917","deaths":"9630","vehicle_miles_traveled_billions":"","populatiom":"103268000","alcohol_related_best":"","alcohol_related_derived":""},
{"year":"1918","deaths":"10390","vehicle_miles_traveled_billions":"","populatiom":"103208000","alcohol_related_best":"","alcohol_related_derived":""},
{"year":"1919","deaths":"10896","vehicle_miles_traveled_billions":"","populatiom":"104514000","alcohol_related_best":"","alcohol_related_derived":""},
{"year":"1920","deaths":"12155","vehicle_miles_traveled_billions":"","populatiom":"106461000","alcohol_related_best":"","alcohol_related_derived":""},
{"year":"1921","deaths":"13253","vehicle_miles_traveled_billions":"55","populatiom":"108538000","alcohol_related_best":"","alcohol_related_derived":""},
{"year":"1922","deaths":"14859","vehicle_miles_traveled_billions":"67","populatiom":"110049000","alcohol_related_best":"","alcohol_related_derived":""},
{"year":"1923","deaths":"17870","vehicle_miles_traveled_billions":"85","populatiom":"111947000","alcohol_related_best":"","alcohol_related_derived":""},
{"year":"1924","deaths":"18400","vehicle_miles_traveled_billions":"104","populatiom":"114109000","alcohol_related_best":"","alcohol_related_derived":""},
{"year":"1925","deaths":"20771","vehicle_miles_traveled_billions":"122","populatiom":"115829000","alcohol_related_best":"","alcohol_related_derived":""},
{"year":"1926","deaths":"22194","vehicle_miles_traveled_billions":"140","populatiom":"117397000","alcohol_related_best":"","alcohol_related_derived":""},
{"year":"1927","deaths":"24470","vehicle_miles_traveled_billions":"158","populatiom":"119035000","alcohol_related_best":"","alcohol_related_derived":""},
{"year":"1928","deaths":"26557","vehicle_miles_traveled_billions":"172","populatiom":"120509000","alcohol_related_best":"","alcohol_related_derived":""},
{"year":"1929","deaths":"29592","vehicle_miles_traveled_billions":"197","populatiom":"121767000","alcohol_related_best":"","alcohol_related_derived":""},
{"year":"1930","deaths":"31204","vehicle_miles_traveled_billions":"206","populatiom":"123076741","alcohol_related_best":"","alcohol_related_derived":""},
{"year":"1931","deaths":"31963","vehicle_miles_traveled_billions":"216","populatiom":"124039648","alcohol_related_best":"","alcohol_related_derived":""},
{"year":"1932","deaths":"27979","vehicle_miles_traveled_billions":"200","populatiom":"124840471","alcohol_related_best":"","alcohol_related_derived":""},
{"year":"1933","deaths":"29746","vehicle_miles_traveled_billions":"200","populatiom":"125578763","alcohol_related_best":"","alcohol_related_derived":""},
{"year":"1934","deaths":"34240","vehicle_miles_traveled_billions":"215","populatiom":"126373773","alcohol_related_best":"","alcohol_related_derived":""},
{"year":"1935","deaths":"34494","vehicle_miles_traveled_billions":"228","populatiom":"127250232","alcohol_related_best":"","alcohol_related_derived":""},
{"year":"1936","deaths":"36126","vehicle_miles_traveled_billions":"252","populatiom":"128053180","alcohol_related_best":"","alcohol_related_derived":""},
{"year":"1937","deaths":"37819","vehicle_miles_traveled_billions":"270","populatiom":"128824829","alcohol_related_best":"","alcohol_related_derived":""},
{"year":"1938","deaths":"31083","vehicle_miles_traveled_billions":"271","populatiom":"129824939","alcohol_related_best":"","alcohol_related_derived":""},
{"year":"1939","deaths":"30895","vehicle_miles_traveled_billions":"285","populatiom":"130879718","alcohol_related_best":"","alcohol_related_derived":""},
{"year":"1940","deaths":"32914","vehicle_miles_traveled_billions":"302","populatiom":"132122446","alcohol_related_best":"","alcohol_related_derived":""},
{"year":"1941","deaths":"38142","vehicle_miles_traveled_billions":"333","populatiom":"133402471","alcohol_related_best":"","alcohol_related_derived":""},
{"year":"1942","deaths":"27007","vehicle_miles_traveled_billions":"268","populatiom":"134859553","alcohol_related_best":"","alcohol_related_derived":""},
{"year":"1943","deaths":"22727","vehicle_miles_traveled_billions":"208","populatiom":"136739353","alcohol_related_best":"","alcohol_related_derived":""},
{"year":"1944","deaths":"23165","vehicle_miles_traveled_billions":"212","populatiom":"138397345","alcohol_related_best":"","alcohol_related_derived":""},
{"year":"1945","deaths":"26785","vehicle_miles_traveled_billions":"250","populatiom":"139928165","alcohol_related_best":"","alcohol_related_derived":""},
{"year":"1946","deaths":"31874","vehicle_miles_traveled_billions":"340","populatiom":"141388566","alcohol_related_best":"","alcohol_related_derived":""},
{"year":"1947","deaths":"31193","vehicle_miles_traveled_billions":"370","populatiom":"144126071","alcohol_related_best":"","alcohol_related_derived":""},
{"year":"1948","deaths":"30775","vehicle_miles_traveled_billions":"397","populatiom":"146631302","alcohol_related_best":"","alcohol_related_derived":""},
{"year":"1949","deaths":"30246","vehicle_miles_traveled_billions":"424","populatiom":"149188130","alcohol_related_best":"","alcohol_related_derived":""},
{"year":"1950","deaths":"33186","vehicle_miles_traveled_billions":"458","populatiom":"152271417","alcohol_related_best":"","alcohol_related_derived":""},
{"year":"1951","deaths":"35309","vehicle_miles_traveled_billions":"491","populatiom":"154877889","alcohol_related_best":"","alcohol_related_derived":""},
{"year":"1952","deaths":"36088","vehicle_miles_traveled_billions":"513","populatiom":"157552740","alcohol_related_best":"","alcohol_related_derived":""},
{"year":"1953","deaths":"36190","vehicle_miles_traveled_billions":"544","populatiom":"160184192","alcohol_related_best":"","alcohol_related_derived":""},
{"year":"1954","deaths":"33890","vehicle_miles_traveled_billions":"561","populatiom":"163025854","alcohol_related_best":"","alcohol_related_derived":""},
{"year":"1955","deaths":"36688","vehicle_miles_traveled_billions":"605","populatiom":"165931202","alcohol_related_best":"","alcohol_related_derived":""},
{"year":"1956","deaths":"37965","vehicle_miles_traveled_billions":"627","populatiom":"168903031","alcohol_related_best":"","alcohol_related_derived":""},
{"year":"1957","deaths":"36932","vehicle_miles_traveled_billions":"647","populatiom":"171984130","alcohol_related_best":"","alcohol_related_derived":""},
{"year":"1958","deaths":"35331","vehicle_miles_traveled_billions":"664","populatiom":"174881904","alcohol_related_best":"","alcohol_related_derived":""},
{"year":"1959","deaths":"36223","vehicle_miles_traveled_billions":"700","populatiom":"177829628","alcohol_related_best":"","alcohol_related_derived":""},
{"year":"1960","deaths":"36399","vehicle_miles_traveled_billions":"718","populatiom":"180671158","alcohol_related_best":"","alcohol_related_derived":""},
{"year":"1961","deaths":"36285","vehicle_miles_traveled_billions":"737","populatiom":"183691481","alcohol_related_best":"","alcohol_related_derived":""},
{"year":"1962","deaths":"38980","vehicle_miles_traveled_billions":"766","populatiom":"186537737","alcohol_related_best":"","alcohol_related_derived":""},
{"year":"1963","deaths":"41723","vehicle_miles_traveled_billions":"805","populatiom":"189241798","alcohol_related_best":"","alcohol_related_derived":""},
{"year":"1964","deaths":"45645","vehicle_miles_traveled_billions":"846","populatiom":"191888791","alcohol_related_best":"","alcohol_related_derived":""},
{"year":"1965","deaths":"47089","vehicle_miles_traveled_billions":"887","populatiom":"194302963","alcohol_related_best":"","alcohol_related_derived":""},
{"year":"1966","deaths":"50894","vehicle_miles_traveled_billions":"925","populatiom":"196560338","alcohol_related_best":"","alcohol_related_derived":""},
{"year":"1967","deaths":"50724","vehicle_miles_traveled_billions":"964","populatiom":"198712056","alcohol_related_best":"","alcohol_related_derived":""},
{"year":"1968","deaths":"52725","vehicle_miles_traveled_billions":"1015","populatiom":"200706052","alcohol_related_best":"","alcohol_related_derived":""},
{"year":"1969","deaths":"53543","vehicle_miles_traveled_billions":"1061","populatiom":"202676946","alcohol_related_best":"","alcohol_related_derived":""},
{"year":"1970","deaths":"52627","vehicle_miles_traveled_billions":"1109","populatiom":"205052174","alcohol_related_best":"","alcohol_related_derived":""},
{"year":"1971","deaths":"52542","vehicle_miles_traveled_billions":"1178","populatiom":"207660677","alcohol_related_best":"","alcohol_related_derived":""},
{"year":"1972","deaths":"54589","vehicle_miles_traveled_billions":"1259","populatiom":"209896021","alcohol_related_best":"","alcohol_related_derived":""},
{"year":"1973","deaths":"54052","vehicle_miles_traveled_billions":"1313","populatiom":"211908788","alcohol_related_best":"","alcohol_related_derived":""},
{"year":"1974","deaths":"45196","vehicle_miles_traveled_billions":"1280","populatiom":"213853928","alcohol_related_best":"","alcohol_related_derived":""},
{"year":"1975","deaths":"44525","vehicle_miles_traveled_billions":"1327","populatiom":"215973199","alcohol_related_best":"","alcohol_related_derived":""},
{"year":"1976","deaths":"45523","vehicle_miles_traveled_billions":"1402","populatiom":"218035164","alcohol_related_best":"","alcohol_related_derived":""},
{"year":"1977","deaths":"47878","vehicle_miles_traveled_billions":"1467","populatiom":"220239425","alcohol_related_best":"","alcohol_related_derived":""},
{"year":"1978","deaths":"50331","vehicle_miles_traveled_billions":"1544","populatiom":"222584545","alcohol_related_best":"","alcohol_related_derived":""},
{"year":"1979","deaths":"51093","vehicle_miles_traveled_billions":"1529","populatiom":"225055487","alcohol_related_best":"","alcohol_related_derived":""},
{"year":"1980","deaths":"51091","vehicle_miles_traveled_billions":"1527","populatiom":"227224681","alcohol_related_best":"","alcohol_related_derived":""},
{"year":"1981","deaths":"49301","vehicle_miles_traveled_billions":"1552","populatiom":"229465714","alcohol_related_best":"","alcohol_related_derived":""},
{"year":"1982","deaths":"43945","vehicle_miles_traveled_billions":"1595","populatiom":"231664458","alcohol_related_best":"21191","alcohol_related_derived":"21191"},
{"year":"1983","deaths":"42589","vehicle_miles_traveled_billions":"1652","populatiom":"233791994","alcohol_related_best":"19958","alcohol_related_derived":"19958"},
{"year":"1984","deaths":"44257","vehicle_miles_traveled_billions":"1720","populatiom":"235824902","alcohol_related_best":"20062","alcohol_related_derived":"20062"},
{"year":"1985","deaths":"43825","vehicle_miles_traveled_billions":"1774","populatiom":"237923795","alcohol_related_best":"18125","alcohol_related_derived":"18994"},
{"year":"1986","deaths":"46087","vehicle_miles_traveled_billions":"1834","populatiom":"240132887","alcohol_related_best":"20081","alcohol_related_derived":"20081"},
{"year":"1987","deaths":"46390","vehicle_miles_traveled_billions":"1921","populatiom":"242288918","alcohol_related_best":"19822","alcohol_related_derived":"19822"},
{"year":"1988","deaths":"47087","vehicle_miles_traveled_billions":"2025","populatiom":"244498982","alcohol_related_best":"19898","alcohol_related_derived":"19898"},
{"year":"1989","deaths":"45582","vehicle_miles_traveled_billions":"2096","populatiom":"246819230","alcohol_related_best":"18603","alcohol_related_derived":"18603"},
{"year":"1990","deaths":"44599","vehicle_miles_traveled_billions":"2144","populatiom":"249464396","alcohol_related_best":"17705","alcohol_related_derived":"18359"},
{"year":"1991","deaths":"41508","vehicle_miles_traveled_billions":"2172","populatiom":"252153092","alcohol_related_best":"16405","alcohol_related_derived":"16405"},
{"year":"1992","deaths":"39250","vehicle_miles_traveled_billions":"2247","populatiom":"255029699","alcohol_related_best":"14603","alcohol_related_derived":"14603"},
{"year":"1993","deaths":"40150","vehicle_miles_traveled_billions":"2296","populatiom":"257782608","alcohol_related_best":"14173","alcohol_related_derived":"14173"},
{"year":"1994","deaths":"40716","vehicle_miles_traveled_billions":"2358","populatiom":"260327021","alcohol_related_best":"13463","alcohol_related_derived":"13463"},
{"year":"1995","deaths":"41817","vehicle_miles_traveled_billions":"2423","populatiom":"262803276","alcohol_related_best":"13478","alcohol_related_derived":""},
{"year":"1996","deaths":"42065","vehicle_miles_traveled_billions":"2486","populatiom":"265228572","alcohol_related_best":"17126","alcohol_related_derived":""},
{"year":"1997","deaths":"42013","vehicle_miles_traveled_billions":"2562","populatiom":"267783607","alcohol_related_best":"16189","alcohol_related_derived":""},
{"year":"1998","deaths":"41501","vehicle_miles_traveled_billions":"2632","populatiom":"270248003","alcohol_related_best":"15935","alcohol_related_derived":""},
{"year":"1999","deaths":"41717","vehicle_miles_traveled_billions":"2691","populatiom":"272690813","alcohol_related_best":"15786","alcohol_related_derived":""},
{"year":"2000","deaths":"41945","vehicle_miles_traveled_billions":"2747","populatiom":"282216952","alcohol_related_best":"13324","alcohol_related_derived":""},
{"year":"2001","deaths":"42196","vehicle_miles_traveled_billions":"2797","populatiom":"285226284","alcohol_related_best":"17400","alcohol_related_derived":""},
{"year":"2002","deaths":"43005","vehicle_miles_traveled_billions":"2856","populatiom":"288125973","alcohol_related_best":"17419","alcohol_related_derived":""},
{"year":"2003","deaths":"42884","vehicle_miles_traveled_billions":"2890","populatiom":"290796023","alcohol_related_best":"17013","alcohol_related_derived":""},
{"year":"2004","deaths":"42836","vehicle_miles_traveled_billions":"2965","populatiom":"293638158","alcohol_related_best":"14409","alcohol_related_derived":""},
{"year":"2005","deaths":"43510","vehicle_miles_traveled_billions":"2989","populatiom":"296507061","alcohol_related_best":"13582","alcohol_related_derived":""},
{"year":"2006","deaths":"42708","vehicle_miles_traveled_billions":"3014","populatiom":"299398484","alcohol_related_best":"13491","alcohol_related_derived":""},
{"year":"2007","deaths":"41259","vehicle_miles_traveled_billions":"3031","populatiom":"301139947","alcohol_related_best":"13041","alcohol_related_derived":""},
{"year":"2008","deaths":"37423","vehicle_miles_traveled_billions":"2977","populatiom":"303824640","alcohol_related_best":"11711","alcohol_related_derived":""},
{"year":"2009","deaths":"33883","vehicle_miles_traveled_billions":"2957","populatiom":"306700000","alcohol_related_best":"10759","alcohol_related_derived":""},
{"year":"2010","deaths":"32999","vehicle_miles_traveled_billions":"2967","populatiom":"309326000","alcohol_related_best":"10136","alcohol_related_derived":""},
{"year":"2011","deaths":"32479","vehicle_miles_traveled_billions":"2950","populatiom":"311588000","alcohol_related_best":"9865","alcohol_related_derived":""},
{"year":"2012","deaths":"33782","vehicle_miles_traveled_billions":"2969","populatiom":"313914000","alcohol_related_best":"10336","alcohol_related_derived":""},
{"year":"2013","deaths":"32893","vehicle_miles_traveled_billions":"2988","populatiom":"316129000","alcohol_related_best":"10110","alcohol_related_derived":""},
{"year":"2014","deaths":"32744","vehicle_miles_traveled_billions":"3026","populatiom":"318860000","alcohol_related_best":"9943","alcohol_related_derived":""},
{"year":"2015","deaths":"35485","vehicle_miles_traveled_billions":"3095","populatiom":"321370000","alcohol_related_best":"10320","alcohol_related_derived":""},
{"year":"2016","deaths":"37806","vehicle_miles_traveled_billions":"3174","populatiom":"323121000","alcohol_related_best":"10996","alcohol_related_derived":""},
{"year":"2017","deaths":"37133","vehicle_miles_traveled_billions":"3213","populatiom":"326213213","alcohol_related_best":"10908","alcohol_related_derived":""},
{"year":"2018","deaths":"36560","vehicle_miles_traveled_billions":"3223","populatiom":"327096265","alcohol_related_best":"10511","alcohol_related_derived":""}
]
